opsicos/_init_.py
opsicos-1.1.2.dist-info/METADATA
opsicos-1.1.2.dist-info/WHEEL
opsicos-1.1.2.dist-info/top_level.txt
opsicos-1.1.2.dist-info/RECORD
