Metadata-Version: 2.4
Name: opsicos
Version: 1.1.2
Summary: A professional Python SDK for the Opsicos AI Gateway.
Author: Tawsif
Requires-Python: >=3.6
Requires-Dist: requests
Dynamic: author
Dynamic: description
Dynamic: description-content-type
Dynamic: requires-dist
Dynamic: requires-python
Dynamic: summary
